specifications/README.md
specifications/__init__.py
specifications/specifications.aac
specifications/specifications_impl.py
aac_spec-0.1.9.dist-info/METADATA
aac_spec-0.1.9.dist-info/WHEEL
aac_spec-0.1.9.dist-info/entry_points.txt
aac_spec-0.1.9.dist-info/top_level.txt
aac_spec-0.1.9.dist-info/RECORD
